ansys/dyna/core/__init__.py
ansys/dyna/core/pre/README.md
ansys/dyna/core/pre/__init__.py
ansys/dyna/core/pre/dynabase.py
ansys/dyna/core/pre/dynadem.py
ansys/dyna/core/pre/dynaem.py
ansys/dyna/core/pre/dynaicfd.py
ansys/dyna/core/pre/dynaiga.py
ansys/dyna/core/pre/dynaisph.py
ansys/dyna/core/pre/dynalogging.py
ansys/dyna/core/pre/dynamaterial.py
ansys/dyna/core/pre/dynamech.py
ansys/dyna/core/pre/dynanvh.py
ansys/dyna/core/pre/dynasale.py
ansys/dyna/core/pre/dynasolution.py
ansys/dyna/core/pre/errors.py
ansys/dyna/core/pre/launcher.py
ansys/dyna/core/pre/misc.py
ansys/dyna/core/pre/model.py
ansys/dyna/core/pre/part.py
ansys/dyna/core/pre/examples/__init__.py
ansys/dyna/core/pre/examples/download_utilities.py
ansys/dyna/core/pre/examples/examples.py
ansys/dyna/core/pre/examples/airbag/airbag_deploy/airbag_deploy.k
ansys/dyna/core/pre/examples/em/em_railgun/em_railgun.k
ansys/dyna/core/pre/examples/em/em_resistive_heating/em_resistive_heating.k
ansys/dyna/core/pre/examples/em/em_resistive_heating_2d/em_resistive_heating_2d.k
ansys/dyna/core/pre/examples/em/em_resistive_heating_2d_isopots/em_resistive_heating_2d_isopots.k
ansys/dyna/core/pre/examples/em/em_resistive_heating_2d_multi_isopots/em_resistive_heating_2d_multi_isopots.k
ansys/dyna/core/pre/examples/em/em_rlc_define_func/em_rlc_define_func.k
ansys/dyna/core/pre/examples/em/em_rlc_isopotential/em_rlc_isopotential.k
ansys/dyna/core/pre/examples/explicit/ball_plate/ball_plate.k
ansys/dyna/core/pre/examples/explicit/belted_dummy/belted_dummy.k
ansys/dyna/core/pre/examples/icfd/cylinder_flow/cylinder_flow.k
ansys/dyna/core/pre/examples/icfd/dam_break/dam_break.k
ansys/dyna/core/pre/examples/icfd/dem_coupling/dem_coupling.k
ansys/dyna/core/pre/examples/icfd/driven_cavity/driven_cavity.k
ansys/dyna/core/pre/examples/icfd/free_convection_flow/free_convection_flow.k
ansys/dyna/core/pre/examples/icfd/imposed_move/imposed_move.k
ansys/dyna/core/pre/examples/icfd/internal_3d_flow/internal_3d_flow.k
ansys_dyna_core-0.5.0.dist-info/LICENSE
ansys_dyna_core-0.5.0.dist-info/WHEEL
ansys_dyna_core-0.5.0.dist-info/METADATA
ansys_dyna_core-0.5.0.dist-info/RECORD
