Metadata-Version: 2.1
Name: ansys-dyna-core
Version: 0.5.0
Summary: Python interface to LS-DYNA Service
Keywords: Ansys,LS-DYNA,gRPC
Author-email: "ANSYS, Inc." <pyansys.core@ansys.com>
Maintainer-email: "ANSYS, Inc." <pyansys.core@ansys.com>
Requires-Python: >=3.9,<4
Classifier: Development Status :: 4 - Beta
Classifier: Intended Audience :: Science/Research
Classifier: Topic :: Scientific/Engineering :: Information Analysis
Classifier: License :: OSI Approved :: MIT License
Classifier: Operating System :: OS Independent
Classifier: Programming Language :: Python :: 3
Classifier: Programming Language :: Python :: 3.9
Classifier: Programming Language :: Python :: 3.10
Classifier: Programming Language :: Python :: 3.11
Classifier: Programming Language :: Python :: 3.12
Requires-Dist: ansys-dpf-core>=0.7.2
Requires-Dist: ansys-api-dyna==0.4.0
Requires-Dist: ansys-platform-instancemanagement~=1.0
Requires-Dist: pyvista>=0.43.4
Requires-Dist: recommonmark==0.7.1 ; extra == "doc"
Requires-Dist: matplotlib==3.9.2 ; extra == "doc"
Requires-Dist: imageio==2.35.1 ; extra == "doc"
Requires-Dist: imageio-ffmpeg==0.5.1 ; extra == "doc"
Requires-Dist: numpydoc==1.8.0 ; extra == "doc"
Requires-Dist: Sphinx==8.0.2 ; extra == "doc"
Requires-Dist: sphinx-autobuild==2024.4.16 ; extra == "doc"
Requires-Dist: sphinxcontrib-websupport==2.0.0 ; extra == "doc"
Requires-Dist: pytest-sphinx==0.6.3 ; extra == "doc"
Requires-Dist: sphinx-notfound-page==1.0.4 ; extra == "doc"
Requires-Dist: sphinx-copybutton==0.5.2 ; extra == "doc"
Requires-Dist: sphinx-gallery==0.17.1 ; extra == "doc"
Requires-Dist: sphinx-autodoc-typehints==2.2.3 ; extra == "doc"
Requires-Dist: ansys-sphinx-theme==1.0.7 ; extra == "doc"
Requires-Dist: pypandoc==1.13 ; extra == "doc"
Requires-Dist: nbsphinx==0.9.5 ; extra == "doc"
Requires-Dist: ipywidgets==8.1.5 ; extra == "doc"
Requires-Dist: joblib==1.4.2 ; extra == "doc"
Requires-Dist: scikit-learn==1.5.1 ; extra == "doc"
Requires-Dist: ipython==8.26.0 ; extra == "doc"
Requires-Dist: jupyterlab==4.2.4 ; extra == "doc"
Requires-Dist: sphinx-jinja==2.0.2 ; extra == "doc"
Requires-Dist: sphinx-autoapi==3.2.1 ; extra == "doc"
Requires-Dist: pyvista==0.44.1 ; extra == "doc"
Requires-Dist: matplotlib==3.9.2 ; extra == "tests"
Requires-Dist: numpy==2.1.0 ; extra == "tests"
Requires-Dist: pytest==8.3.2 ; extra == "tests"
Requires-Dist: pytest-cov==5.0.0 ; extra == "tests"
Requires-Dist: joblib==1.4.2 ; extra == "tests"
Requires-Dist: pandas==2.2.2 ; extra == "tests"
Requires-Dist: openpyxl==3.1.5 ; extra == "tests"
Requires-Dist: scikit-learn==1.5.1 ; extra == "tests"
Requires-Dist: pytest-xdist==3.6.1 ; extra == "tests"
Requires-Dist: ipython==8.26.0 ; extra == "tests"
Requires-Dist: pyvista==0.44.1 ; extra == "tests"
Project-URL: Documentation, https://dyna.docs.pyansys.com
Project-URL: Homepage, https://dyna.docs.pyansys.com
Project-URL: Source, https://github.com/pyansys/pydyna
Project-URL: Tracker, https://github.com/pyansys/pydyna/issues
Provides-Extra: doc
Provides-Extra: tests
